.gitignore
CHANGES.txt
COPYING.txt
README.rst
README.txt
maintenance.ini
runtests.py
setup.cfg
setup.py
kotti_dkbase/__init__.py
kotti_dkbase/config.ini
kotti_dkbase/configure.zcml
kotti_dkbase/debug.ini
kotti_dkbase/maintenance.py
kotti_dkbase/views.py
kotti_dkbase.egg-info/PKG-INFO
kotti_dkbase.egg-info/SOURCES.txt
kotti_dkbase.egg-info/dependency_links.txt
kotti_dkbase.egg-info/entry_points.txt
kotti_dkbase.egg-info/not-zip-safe
kotti_dkbase.egg-info/requires.txt
kotti_dkbase.egg-info/top_level.txt
kotti_dkbase/kotti-overrides/templates/view/document.pt
kotti_dkbase/kotti-overrides/templates/view/master.pt
kotti_dkbase/kotti-overrides/templates/view/nav-local.pt
kotti_dkbase/kotti-overrides/templates/view/nav.pt
kotti_dkbase/static/edit.css
kotti_dkbase/static/layout.css
kotti_dkbase/static/maintenance.html
kotti_dkbase/static/primary-navigation.css
kotti_dkbase/static/media_icons/facebook.png
kotti_dkbase/static/media_icons/license.txt
kotti_dkbase/static/media_icons/twitter.png
kotti_dkbase/templates/view/base-layout.pt
kotti_dkbase/templates/view/error-404.pt
kotti_dkbase/templates/view/error.pt
kotti_dkbase/templates/view/layout.pt
kotti_dkbase/templates/view/master-footer.pt
kotti_dkbase/templates/view/master-header.pt
kotti_dkbase/templates/view/master-kotti-headers.pt
kotti_dkbase/templates/view/master-layout-headers.pt
kotti_dkbase/templates/view/primary-navigation.pt
kotti_dkbase/tests/test_maintenance.py