Metadata-Version: 1.1
Name: kotti-dkbase
Version: 0.1.0b2
Summary: Kotti setup and modifications for CMS projects of Datenkarussell.
Home-page: https://github.com/chrneumann/kotti_dkbase
Author: Christian Neumann
Author-email: cneumann@datenkarussell.de
License: BSD3
Platform: UNKNOWN
Classifier: Topic :: Internet :: WWW/HTTP :: WSGI :: Application
Classifier: Topic :: Internet :: WWW/HTTP :: Dynamic Content
Classifier: Programming Language :: Python
Classifier: Topic :: Internet :: WWW/HTTP
Classifier: Development Status :: 4 - Beta
Classifier: License :: OSI Approved :: BSD License
Classifier: Framework :: Pylons
